<?xml version="1.0" encoding="UTF-8"?><root><Row_ID>3262</Row_ID><Order_ID>23360</Order_ID><Order_Date>5/11/09</Order_Date><Order_Priority>Low</Order_Priority><Order_Quantity>30</Order_Quantity><Sales>512.97</Sales><Discount>0.01</Discount><Ship_Mode>Express Air</Ship_Mode><Profit>261.29</Profit><Unit_Price>15.67</Unit_Price><Shipping_Cost>1.39</Shipping_Cost><Customer_Name>Jocasta Rupert</Customer_Name><Province>New Brunswick</Province><Region>Atlantic</Region><Customer_Segment>Consumer</Customer_Segment><Product_Category>Office Supplies</Product_Category><Product_Sub-Category>Envelopes</Product_Sub-Category><Product_Name>#10 White Business Envelopes,4 1/8 x 9 1/2</Product_Name><Product_Container>Small Box</Product_Container><Product_Base_Margin>0.38</Product_Base_Margin><Ship_Date>5/11/09</Ship_Date></root>