<?xml version="1.0" encoding="UTF-8"?><root><Row_ID>4182</Row_ID><Order_ID>29700</Order_ID><Order_Date>4/6/10</Order_Date><Order_Priority>Medium</Order_Priority><Order_Quantity>9</Order_Quantity><Sales>30.35</Sales><Discount>0.01</Discount><Ship_Mode>Regular Air</Ship_Mode><Profit>5.02</Profit><Unit_Price>3.08</Unit_Price><Shipping_Cost>0.99</Shipping_Cost><Customer_Name>Eric Barreto</Customer_Name><Province>Quebec</Province><Region>Quebec</Region><Customer_Segment>Consumer</Customer_Segment><Product_Category>Office Supplies</Product_Category><Product_Sub-Category>Labels</Product_Sub-Category><Product_Name>Avery 481</Product_Name><Product_Container>Small Box</Product_Container><Product_Base_Margin>0.37</Product_Base_Margin><Ship_Date>4/7/10</Ship_Date></root>