<?xml version="1.0" encoding="UTF-8"?><root><Row_ID>7560</Row_ID><Order_ID>54084</Order_ID><Order_Date>9/10/11</Order_Date><Order_Priority>Critical</Order_Priority><Order_Quantity>3</Order_Quantity><Sales>160.52</Sales><Discount>0.08</Discount><Ship_Mode>Delivery Truck</Ship_Mode><Profit>-69.66</Profit><Unit_Price>50.98</Unit_Price><Shipping_Cost>14.19</Shipping_Cost><Customer_Name>Lauren Leatherbury</Customer_Name><Province>Alberta</Province><Region>West</Region><Customer_Segment>Corporate</Customer_Segment><Product_Category>Furniture</Product_Category><Product_Sub-Category>Chairs &amp; Chairmats</Product_Sub-Category><Product_Name>Global Deluxe Stacking Chair, Gray</Product_Name><Product_Container>Jumbo Drum</Product_Container><Product_Base_Margin>0.56</Product_Base_Margin><Ship_Date>9/12/11</Ship_Date></root>