<?xml version="1.0" encoding="UTF-8"?><root><Row_ID>822</Row_ID><Order_ID>5925</Order_ID><Order_Date>11/12/11</Order_Date><Order_Priority>Low</Order_Priority><Order_Quantity>25</Order_Quantity><Sales>1733.3625</Sales><Discount>0.07</Discount><Ship_Mode>Regular Air</Ship_Mode><Profit>-267.01</Profit><Unit_Price>85.99</Unit_Price><Shipping_Cost>0.99</Shipping_Cost><Customer_Name>Joy Bell</Customer_Name><Province>Nunavut</Province><Region>Nunavut</Region><Customer_Segment>Home Office</Customer_Segment><Product_Category>Technology</Product_Category><Product_Sub-Category>Telephones and Communication</Product_Sub-Category><Product_Name>Accessory4</Product_Name><Product_Container>Wrap Bag</Product_Container><Product_Base_Margin>0.85</Product_Base_Margin><Ship_Date>11/19/11</Ship_Date></root>