<Order OrderID="10427">
	<CustomerID>PICCO</CustomerID>
	<EmployeeID>4</EmployeeID>
	<OrderDate>1997-01-27T23:05:25</OrderDate>
	<RequiredDate>1997-02-24T06:41:47</RequiredDate>
	<ShippedDate>1997-03-03T01:47:37</ShippedDate>
	<ShipVia>2</ShipVia>
	<Freight>31.2900</Freight>
	<ShipName>Piccolo und mehr</ShipName>
	<ShipAddress>Geislweg 14</ShipAddress>
	<ShipCity>Salzburg</ShipCity>
	<ShipRegion/>
	<ShipPostalCode>5020</ShipPostalCode>
	<ShipCountry>Austria</ShipCountry>
	<OrderDetails>
		<OrderDetail>
			<ProductID>14</ProductID>
			<UnitPrice>18.6000</UnitPrice>
			<Quantity>35</Quantity>
			<Discount>0</Discount>
		</OrderDetail>
	</OrderDetails>
</Order>

