<Order OrderID="10492">
	<CustomerID>BOTTM</CustomerID>
	<EmployeeID>3</EmployeeID>
	<OrderDate>1997-04-01T16:14:47</OrderDate>
	<RequiredDate>1997-04-29T09:58:55</RequiredDate>
	<ShippedDate>1997-04-11T15:22:02</ShippedDate>
	<ShipVia>1</ShipVia>
	<Freight>62.8900</Freight>
	<ShipName>Bottom-Dollar Markets</ShipName>
	<ShipAddress>23 Tsawassen Blvd.</ShipAddress>
	<ShipCity>Tsawassen</ShipCity>
	<ShipRegion>BC</ShipRegion>
	<ShipPostalCode>T2F 8M4</ShipPostalCode>
	<ShipCountry>Canada</ShipCountry>
	<OrderDetails>
		<OrderDetail>
			<ProductID>25</ProductID>
			<UnitPrice>11.2000</UnitPrice>
			<Quantity>60</Quantity>
			<Discount>0.05</Discount>
		</OrderDetail>
		<OrderDetail>
			<ProductID>42</ProductID>
			<UnitPrice>11.2000</UnitPrice>
			<Quantity>20</Quantity>
			<Discount>0.05</Discount>
		</OrderDetail>
	</OrderDetails>
</Order>

