<Order OrderID="10771">
	<CustomerID>ERNSH</CustomerID>
	<EmployeeID>9</EmployeeID>
	<OrderDate>1997-12-10T01:30:03</OrderDate>
	<RequiredDate>1998-01-07T16:33:25</RequiredDate>
	<ShippedDate>1998-01-02T01:38:16</ShippedDate>
	<ShipVia>2</ShipVia>
	<Freight>11.1900</Freight>
	<ShipName>Ernst Handel</ShipName>
	<ShipAddress>Kirchgasse 6</ShipAddress>
	<ShipCity>Graz</ShipCity>
	<ShipRegion/>
	<ShipPostalCode>8010</ShipPostalCode>
	<ShipCountry>Austria</ShipCountry>
	<OrderDetails>
		<OrderDetail>
			<ProductID>71</ProductID>
			<UnitPrice>21.5000</UnitPrice>
			<Quantity>16</Quantity>
			<Discount>0</Discount>
		</OrderDetail>
	</OrderDetails>
</Order>

