<Order OrderID="10970">
	<CustomerID>BOLID</CustomerID>
	<EmployeeID>9</EmployeeID>
	<OrderDate>1998-03-24T06:41:30</OrderDate>
	<RequiredDate>1998-04-07T08:53:50</RequiredDate>
	<ShippedDate>1998-04-24T00:15:54</ShippedDate>
	<ShipVia>1</ShipVia>
	<Freight>16.1600</Freight>
	<ShipName>Bólido Comidas preparadas</ShipName>
	<ShipAddress>C/ Araquil, 67</ShipAddress>
	<ShipCity>Madrid</ShipCity>
	<ShipRegion/>
	<ShipPostalCode>28023</ShipPostalCode>
	<ShipCountry>Spain</ShipCountry>
	<OrderDetails>
		<OrderDetail>
			<ProductID>52</ProductID>
			<UnitPrice>7.0000</UnitPrice>
			<Quantity>40</Quantity>
			<Discount>0.2</Discount>
		</OrderDetail>
	</OrderDetails>
</Order>

