<Order OrderID="11077">
	<CustomerID>RATTC</CustomerID>
	<EmployeeID>1</EmployeeID>
	<OrderDate>1998-05-06T01:37:09</OrderDate>
	<RequiredDate>1998-06-03T15:45:09</RequiredDate>
	<ShipVia>2</ShipVia>
	<Freight>8.5300</Freight>
	<ShipName>Rattlesnake Canyon Grocery</ShipName>
	<ShipAddress>2817 Milton Dr.</ShipAddress>
	<ShipCity>Albuquerque</ShipCity>
	<ShipRegion>NM</ShipRegion>
	<ShipPostalCode>87110</ShipPostalCode>
	<ShipCountry>USA</ShipCountry>
	<OrderDetails>
		<OrderDetail>
			<ProductID>2</ProductID>
			<UnitPrice>19.0000</UnitPrice>
			<Quantity>24</Quantity>
			<Discount>0.2</Discount>
		</OrderDetail>
		<OrderDetail>
			<ProductID>3</ProductID>
			<UnitPrice>10.0000</UnitPrice>
			<Quantity>4</Quantity>
			<Discount>0</Discount>
		</OrderDetail>
		<OrderDetail>
			<ProductID>4</ProductID>
			<UnitPrice>22.0000</UnitPrice>
			<Quantity>1</Quantity>
			<Discount>0</Discount>
		</OrderDetail>
		<OrderDetail>
			<ProductID>6</ProductID>
			<UnitPrice>25.0000</UnitPrice>
			<Quantity>1</Quantity>
			<Discount>0.02</Discount>
		</OrderDetail>
		<OrderDetail>
			<ProductID>7</ProductID>
			<UnitPrice>30.0000</UnitPrice>
			<Quantity>1</Quantity>
			<Discount>0.05</Discount>
		</OrderDetail>
		<OrderDetail>
			<ProductID>8</ProductID>
			<UnitPrice>40.0000</UnitPrice>
			<Quantity>2</Quantity>
			<Discount>0.1</Discount>
		</OrderDetail>
		<OrderDetail>
			<ProductID>10</ProductID>
			<UnitPrice>31.0000</UnitPrice>
			<Quantity>1</Quantity>
			<Discount>0</Discount>
		</OrderDetail>
		<OrderDetail>
			<ProductID>12</ProductID>
			<UnitPrice>38.0000</UnitPrice>
			<Quantity>2</Quantity>
			<Discount>0.05</Discount>
		</OrderDetail>
		<OrderDetail>
			<ProductID>13</ProductID>
			<UnitPrice>6.0000</UnitPrice>
			<Quantity>4</Quantity>
			<Discount>0</Discount>
		</OrderDetail>
		<OrderDetail>
			<ProductID>14</ProductID>
			<UnitPrice>23.2500</UnitPrice>
			<Quantity>1</Quantity>
			<Discount>0.03</Discount>
		</OrderDetail>
		<OrderDetail>
			<ProductID>16</ProductID>
			<UnitPrice>17.4500</UnitPrice>
			<Quantity>2</Quantity>
			<Discount>0.03</Discount>
		</OrderDetail>
		<OrderDetail>
			<ProductID>20</ProductID>
			<UnitPrice>81.0000</UnitPrice>
			<Quantity>1</Quantity>
			<Discount>0.04</Discount>
		</OrderDetail>
		<OrderDetail>
			<ProductID>23</ProductID>
			<UnitPrice>9.0000</UnitPrice>
			<Quantity>2</Quantity>
			<Discount>0</Discount>
		</OrderDetail>
		<OrderDetail>
			<ProductID>32</ProductID>
			<UnitPrice>32.0000</UnitPrice>
			<Quantity>1</Quantity>
			<Discount>0</Discount>
		</OrderDetail>
		<OrderDetail>
			<ProductID>39</ProductID>
			<UnitPrice>18.0000</UnitPrice>
			<Quantity>2</Quantity>
			<Discount>0.05</Discount>
		</OrderDetail>
		<OrderDetail>
			<ProductID>41</ProductID>
			<UnitPrice>9.6500</UnitPrice>
			<Quantity>3</Quantity>
			<Discount>0</Discount>
		</OrderDetail>
		<OrderDetail>
			<ProductID>46</ProductID>
			<UnitPrice>12.0000</UnitPrice>
			<Quantity>3</Quantity>
			<Discount>0.02</Discount>
		</OrderDetail>
		<OrderDetail>
			<ProductID>52</ProductID>
			<UnitPrice>7.0000</UnitPrice>
			<Quantity>2</Quantity>
			<Discount>0</Discount>
		</OrderDetail>
		<OrderDetail>
			<ProductID>55</ProductID>
			<UnitPrice>24.0000</UnitPrice>
			<Quantity>2</Quantity>
			<Discount>0</Discount>
		</OrderDetail>
		<OrderDetail>
			<ProductID>60</ProductID>
			<UnitPrice>34.0000</UnitPrice>
			<Quantity>2</Quantity>
			<Discount>0.06</Discount>
		</OrderDetail>
		<OrderDetail>
			<ProductID>64</ProductID>
			<UnitPrice>33.2500</UnitPrice>
			<Quantity>2</Quantity>
			<Discount>0.03</Discount>
		</OrderDetail>
		<OrderDetail>
			<ProductID>66</ProductID>
			<UnitPrice>17.0000</UnitPrice>
			<Quantity>1</Quantity>
			<Discount>0</Discount>
		</OrderDetail>
		<OrderDetail>
			<ProductID>73</ProductID>
			<UnitPrice>15.0000</UnitPrice>
			<Quantity>2</Quantity>
			<Discount>0.01</Discount>
		</OrderDetail>
		<OrderDetail>
			<ProductID>75</ProductID>
			<UnitPrice>7.7500</UnitPrice>
			<Quantity>4</Quantity>
			<Discount>0</Discount>
		</OrderDetail>
		<OrderDetail>
			<ProductID>77</ProductID>
			<UnitPrice>13.0000</UnitPrice>
			<Quantity>2</Quantity>
			<Discount>0</Discount>
		</OrderDetail>
	</OrderDetails>
</Order>

