<?xml version="1.0" encoding="UTF-8"?><root><BusinessEntityID>1756</BusinessEntityID><Title>Mr.</Title><FirstName>Marty</FirstName><MiddleName>E.</MiddleName><LastName>Simpson</LastName><Suffix>NULL</Suffix><PhoneNumber>288-555-0100</PhoneNumber><PhoneNumberType>Cell</PhoneNumberType><EmailAddress>marty0@adventure-works.com</EmailAddress><EmailPromotion>0</EmailPromotion><AddressType>Home</AddressType><AddressLine1>1937 Sycamore Drive</AddressLine1><AddressLine2>NULL</AddressLine2><City>Bellingham</City><StateProvinceName>Washington</StateProvinceName><PostalCode>98225</PostalCode><CountryRegionName>United States</CountryRegionName><Demographics>&lt;IndividualSurvey xmlns="http://schemas.microsoft.com/sqlserver/2004/07/adventure-works/IndividualSurvey"&gt;&lt;TotalPurchaseYTD&gt;2389.0618&lt;/TotalPurchaseYTD&gt;&lt;DateFirstPurchase&gt;2002-08-26Z&lt;/DateFirstPurchase&gt;&lt;BirthDate&gt;1971-08-26Z&lt;/BirthDate&gt;&lt;MaritalStatus&gt;M&lt;/MaritalStatus&gt;&lt;YearlyIncome&gt;50001-75000&lt;/YearlyIncome&gt;&lt;Gender&gt;F&lt;/Gender&gt;&lt;TotalChildren&gt;1&lt;/TotalChildren&gt;&lt;NumberChildrenAtHome&gt;1&lt;/NumberChildrenAtHome&gt;&lt;Education&gt;Graduate Degree&lt;/Education&gt;&lt;Occupation&gt;Skilled Manual&lt;/Occupation&gt;&lt;HomeOwnerFlag&gt;1&lt;/HomeOwnerFlag&gt;&lt;NumberCarsOwned&gt;0&lt;/NumberCarsOwned&gt;&lt;CommuteDistance&gt;0-1 Miles&lt;/CommuteDistance&gt;&lt;/IndividualSurvey&gt;</Demographics></root>