<?xml version="1.0" encoding="UTF-8"?><root><Row_ID>1236</Row_ID><Order_ID>8998</Order_ID><Order_Date>1/3/10</Order_Date><Order_Priority>Low</Order_Priority><Order_Quantity>13</Order_Quantity><Sales>178.13</Sales><Discount>0.04</Discount><Ship_Mode>Regular Air</Ship_Mode><Profit>-19.75</Profit><Unit_Price>13.43</Unit_Price><Shipping_Cost>5.5</Shipping_Cost><Customer_Name>Linda Southworth</Customer_Name><Province>Manitoba</Province><Region>Prarie</Region><Customer_Segment>Consumer</Customer_Segment><Product_Category>Office Supplies</Product_Category><Product_Sub-Category>Storage &amp; Organization</Product_Sub-Category><Product_Name>Fellowes Personal Hanging Folder Files, Navy</Product_Name><Product_Container>Small Box</Product_Container><Product_Base_Margin>0.57</Product_Base_Margin><Ship_Date>1/8/10</Ship_Date></root>