<?xml version="1.0" encoding="UTF-8"?><root><Row_ID>3490</Row_ID><Order_ID>24869</Order_ID><Order_Date>6/10/09</Order_Date><Order_Priority>Not Specified</Order_Priority><Order_Quantity>14</Order_Quantity><Sales>132.72</Sales><Discount>0.05</Discount><Ship_Mode>Regular Air</Ship_Mode><Profit>-9.18</Profit><Unit_Price>8.85</Unit_Price><Shipping_Cost>5.6</Shipping_Cost><Customer_Name>Nat Gilpin</Customer_Name><Province>Ontario</Province><Region>Ontario</Region><Customer_Segment>Consumer</Customer_Segment><Product_Category>Office Supplies</Product_Category><Product_Sub-Category>Binders and Binder Accessories</Product_Sub-Category><Product_Name>GBC Standard Plastic Binding Systems Combs</Product_Name><Product_Container>Small Box</Product_Container><Product_Base_Margin>0.36</Product_Base_Margin><Ship_Date>6/11/09</Ship_Date></root>