<?xml version="1.0" encoding="UTF-8"?><root><Row_ID>6608</Row_ID><Order_ID>47012</Order_ID><Order_Date>5/13/10</Order_Date><Order_Priority>Low</Order_Priority><Order_Quantity>35</Order_Quantity><Sales>584.42</Sales><Discount>0.08</Discount><Ship_Mode>Express Air</Ship_Mode><Profit>-97.21</Profit><Unit_Price>16.99</Unit_Price><Shipping_Cost>8.99</Shipping_Cost><Customer_Name>Michael Oakman</Customer_Name><Province>Quebec</Province><Region>Quebec</Region><Customer_Segment>Small Business</Customer_Segment><Product_Category>Office Supplies</Product_Category><Product_Sub-Category>Pens &amp; Art Supplies</Product_Sub-Category><Product_Name>Berol Giant Pencil Sharpener</Product_Name><Product_Container>Small Pack</Product_Container><Product_Base_Margin>0.56</Product_Base_Margin><Ship_Date>5/17/10</Ship_Date></root>