<?xml version="1.0" encoding="UTF-8"?><root><Row_ID>7845</Row_ID><Order_ID>56101</Order_ID><Order_Date>7/19/10</Order_Date><Order_Priority>Not Specified</Order_Priority><Order_Quantity>1</Order_Quantity><Sales>21.45</Sales><Discount>0.01</Discount><Ship_Mode>Regular Air</Ship_Mode><Profit>-7.22</Profit><Unit_Price>14.42</Unit_Price><Shipping_Cost>6.75</Shipping_Cost><Customer_Name>Bill Donatelli</Customer_Name><Province>Ontario</Province><Region>Ontario</Region><Customer_Segment>Corporate</Customer_Segment><Product_Category>Office Supplies</Product_Category><Product_Sub-Category>Appliances</Product_Sub-Category><Product_Name>Holmes Odor Grabber</Product_Name><Product_Container>Medium Box</Product_Container><Product_Base_Margin>0.52</Product_Base_Margin><Ship_Date>7/21/10</Ship_Date></root>