<Order OrderID="10432">
	<CustomerID>SPLIR</CustomerID>
	<EmployeeID>3</EmployeeID>
	<OrderDate>1997-01-31T10:01:16</OrderDate>
	<RequiredDate>1997-02-14T11:14:45</RequiredDate>
	<ShippedDate>1997-02-07T23:00:55</ShippedDate>
	<ShipVia>2</ShipVia>
	<Freight>4.3400</Freight>
	<ShipName>Split Rail Beer &amp; Ale</ShipName>
	<ShipAddress>P.O. Box 555</ShipAddress>
	<ShipCity>Lander</ShipCity>
	<ShipRegion>WY</ShipRegion>
	<ShipPostalCode>82520</ShipPostalCode>
	<ShipCountry>USA</ShipCountry>
	<OrderDetails>
		<OrderDetail>
			<ProductID>26</ProductID>
			<UnitPrice>24.9000</UnitPrice>
			<Quantity>10</Quantity>
			<Discount>0</Discount>
		</OrderDetail>
		<OrderDetail>
			<ProductID>54</ProductID>
			<UnitPrice>5.9000</UnitPrice>
			<Quantity>40</Quantity>
			<Discount>0</Discount>
		</OrderDetail>
	</OrderDetails>
</Order>

