<Order OrderID="10540">
	<CustomerID>QUICK</CustomerID>
	<EmployeeID>3</EmployeeID>
	<OrderDate>1997-05-19T13:56:37</OrderDate>
	<RequiredDate>1997-06-16T18:19:50</RequiredDate>
	<ShippedDate>1997-06-13T03:26:03</ShippedDate>
	<ShipVia>3</ShipVia>
	<Freight>1007.6400</Freight>
	<ShipName>QUICK-Stop</ShipName>
	<ShipAddress>Taucherstraße 10</ShipAddress>
	<ShipCity>Cunewalde</ShipCity>
	<ShipRegion/>
	<ShipPostalCode>01307</ShipPostalCode>
	<ShipCountry>Germany</ShipCountry>
	<OrderDetails>
		<OrderDetail>
			<ProductID>3</ProductID>
			<UnitPrice>10.0000</UnitPrice>
			<Quantity>60</Quantity>
			<Discount>0</Discount>
		</OrderDetail>
		<OrderDetail>
			<ProductID>26</ProductID>
			<UnitPrice>31.2300</UnitPrice>
			<Quantity>40</Quantity>
			<Discount>0</Discount>
		</OrderDetail>
		<OrderDetail>
			<ProductID>38</ProductID>
			<UnitPrice>263.5000</UnitPrice>
			<Quantity>30</Quantity>
			<Discount>0</Discount>
		</OrderDetail>
		<OrderDetail>
			<ProductID>68</ProductID>
			<UnitPrice>12.5000</UnitPrice>
			<Quantity>35</Quantity>
			<Discount>0</Discount>
		</OrderDetail>
	</OrderDetails>
</Order>

